aws2wrap/__init__.py
aws2_wrap2-2.0.1.dist-info/LICENSE
aws2_wrap2-2.0.1.dist-info/METADATA
aws2_wrap2-2.0.1.dist-info/WHEEL
aws2_wrap2-2.0.1.dist-info/entry_points.txt
aws2_wrap2-2.0.1.dist-info/top_level.txt
aws2_wrap2-2.0.1.dist-info/RECORD
