Metadata-Version: 2.1
Name: aws2-wrap2
Version: 2.0.1
Summary: A wrapper for executing a command with AWS CLI v2 and SSO
Home-page: https://github.com/bigwheel/aws2-wrap
Author: Philip Colmer
Author-email: k.bigwheel+eng@gmail.com
License: GNU General Public License v3 (GPLv3)
Keywords: aws profile sso assume role
Platform: UNKNOWN
Classifier: Development Status :: 4 - Beta
Classifier: Intended Audience :: Developers
Classifier: Programming Language :: Python :: 3
Classifier: Environment :: Console
Classifier: License :: OSI Approved :: GNU General Public License v3 (GPLv3)
Classifier: Operating System :: OS Independent
Requires-Python: >=3.6
